image2ascii/__init__.py
image2ascii/converter.py
pyimg2ascii-0.5.dist-info/licenses/LICENSE
pyimg2ascii-0.5.dist-info/METADATA
pyimg2ascii-0.5.dist-info/WHEEL
pyimg2ascii-0.5.dist-info/top_level.txt
pyimg2ascii-0.5.dist-info/RECORD
