Metadata-Version: 2.4
Name: pyimg2ascii
Version: 0.5
Summary: Convert images to ASCII art
Home-page: https://github.com/abhirammdh/pyimg2ascii
Author: Devulapalli Abhiram
Author-email: abhiramdevulapalli8@gmail.com
Classifier: Programming Language :: Python :: 3
Classifier: License :: OSI Approved :: MIT License
Requires-Python: >=3.7
License-File: LICENSE
Requires-Dist: pillow
Dynamic: author
Dynamic: author-email
Dynamic: classifier
Dynamic: description
Dynamic: description-content-type
Dynamic: home-page
Dynamic: license-file
Dynamic: requires-dist
Dynamic: requires-python
Dynamic: summary
